AUTHORS
CHANGELOG.txt
DESCRIPTION
LICENSE
MANIFEST.in
README.rst
setup.py
django_event_rsvp.egg-info/PKG-INFO
django_event_rsvp.egg-info/SOURCES.txt
django_event_rsvp.egg-info/dependency_links.txt
django_event_rsvp.egg-info/requires.txt
django_event_rsvp.egg-info/top_level.txt
event_rsvp/__init__.py
event_rsvp/admin.py
event_rsvp/cms_plugins.py
event_rsvp/forms.py
event_rsvp/models.py
event_rsvp/settings.py
event_rsvp/signals.py
event_rsvp/urls.py
event_rsvp/views.py
event_rsvp/forms/__init__.py
event_rsvp/forms/base.py
event_rsvp/locale/de/LC_MESSAGES/django.mo
event_rsvp/locale/de/LC_MESSAGES/django.po
event_rsvp/migrations/0001_initial.py
event_rsvp/migrations/0002_auto__del_field_event_require_name_and_email__add_field_event_required.py
event_rsvp/migrations/0003_auto__add_field_guest_is_attending__add_field_guest_message.py
event_rsvp/migrations/0004_auto__chg_field_event_title.py
event_rsvp/migrations/0005_auto__add_field_event_hide_available_seats.py
event_rsvp/migrations/0006_auto__chg_field_event_max_seats_per_guest.py
event_rsvp/migrations/0007_auto__chg_field_event_slug.py
event_rsvp/migrations/0008_auto__add_field_event_is_published.py
event_rsvp/migrations/0009_auto__add_field_event_image.py
event_rsvp/migrations/__init__.py
event_rsvp/templates/event_rsvp/event_confirm_delete.html
event_rsvp/templates/event_rsvp/event_detail.html
event_rsvp/templates/event_rsvp/event_form.html
event_rsvp/templates/event_rsvp/event_list.html
event_rsvp/templates/event_rsvp/guest_confirm_delete.html
event_rsvp/templates/event_rsvp/guest_detail.html
event_rsvp/templates/event_rsvp/guest_form.html
event_rsvp/templates/event_rsvp/staff_dashboard.html
event_rsvp/templates/event_rsvp/upcoming_events.html
event_rsvp/templates/event_rsvp/partials/event_item.html
event_rsvp/tests/__init__.py
event_rsvp/tests/cmsplugin_tests.py
event_rsvp/tests/factories.py
event_rsvp/tests/forms_tests.py
event_rsvp/tests/models_tests.py
event_rsvp/tests/runtests.py
event_rsvp/tests/south_settings.py
event_rsvp/tests/test_settings.py
event_rsvp/tests/urls.py
event_rsvp/tests/integration_tests/views_tests.py
event_rsvp/tests/test_app/__init__.py
event_rsvp/tests/test_app/models.py
