Metadata-Version: 1.0
Name: django-event-rsvp
Version: 0.4.1
Summary: A reusable Django app to create event pages where users can RSVP.
